stampchecker/Controller.py
stampchecker/__init__.py
stampchecker/__main__.py
stampchecker-1.0.0.dist-info/LICENSE.md
stampchecker-1.0.0.dist-info/METADATA
stampchecker-1.0.0.dist-info/WHEEL
stampchecker-1.0.0.dist-info/entry_points.txt
stampchecker-1.0.0.dist-info/top_level.txt
stampchecker-1.0.0.dist-info/RECORD
