Metadata-Version: 2.1
Name: stampchecker
Version: 1.0.0
Summary: Check timestamp manipulation based on TSK body file
Home-page: https://github.com/5f0ne/stampchecker
Author: 5f0
License: MIT
Classifier: Operating System :: OS Independent 
Classifier: Programming Language :: Python :: 3 
Classifier: License :: OSI Approved :: MIT License 
License-File: LICENSE.md
